Metadata-Version: 2.1
Name: xregistration
Version: 0.0.1
Summary: Robust astrometric registration and cross-match of astronomical catalogs.
Home-page: https://github.com/rlwastro/robust-registration
Author: Richard L. White
Author-email: rlw@stsci.edu
License: UNKNOWN
Platform: OS Independent
Classifier: Development Status :: 3 - Alpha
Classifier: Intended Audience :: Developers
Classifier: Intended Audience :: Science/Research
Classifier: License :: OSI Approved :: MIT License
Classifier: Operating System :: OS Independent
Classifier: Programming Language :: Python
Requires-Python: >=3.5
License-File: LICENSE.txt
